{
    "$schema": "http://json-schema.org/draft-07/schema#",
    "title": "PromptCreateAvatarResult",
    "description": "PromptCreateAvatarResult",
    "type": "object",
    "properties": {
        "PromptCreateAvatarResult": {
            "$ref": "#/definitions/Enum"
        }
    },
    "definitions": {
        "Enum": {
            "enum": [
                "Success",
                "PermissionDenied",
                "Timeout",
                "UploadFailed",
                "NoUserInput",
                "InvalidHumanoidDescription",
                "UGCValidationFailed",
                "ModeratedName",
                "MaxOutfits",
                "PurchaseFailure",
                "UnknownFailure",
                "TokenInvalid"
            ]
        }
    }
}